infotracker/__init__.py
infotracker/__main__.py
infotracker/adapters.py
infotracker/cli.py
infotracker/config.py
infotracker/diff.py
infotracker/engine.py
infotracker/io_utils.py
infotracker/lineage.py
infotracker/models.py
infotracker/object_db_registry.py
infotracker/openlineage_utils.py
infotracker/parser.py
infotracker/viz.py
infotracker/parser_modules/create_handlers.py
infotracker/parser_modules/db_infer.py
infotracker/parser_modules/deps.py
infotracker/parser_modules/dml.py
infotracker/parser_modules/functions.py
infotracker/parser_modules/names.py
infotracker/parser_modules/preprocess.py
infotracker/parser_modules/procedures.py
infotracker/parser_modules/select_lineage.py
infotracker/parser_modules/string_fallbacks.py
infotracker/parser_modules/temp_utils.py
infotracker/infotracker.yml
infotracker-0.7.0.dist-info/METADATA
infotracker-0.7.0.dist-info/WHEEL
infotracker-0.7.0.dist-info/entry_points.txt
infotracker-0.7.0.dist-info/RECORD
