Metadata-Version: 2.4
Name: InfoTracker
Version: 0.7.0
Summary: Column-level SQL lineage, impact analysis, and breaking-change detection (MS SQL first)
Project-URL: homepage, https://example.com/infotracker
Project-URL: documentation, https://example.com/infotracker/docs
Author: InfoTracker Authors
License: MIT
Keywords: data-lineage,impact-analysis,lineage,mssql,openlineage,sql
Classifier: Environment :: Console
Classifier: License :: OSI Approved :: MIT License
Classifier: Operating System :: OS Independent
Classifier: Programming Language :: Python :: 3
Classifier: Programming Language :: Python :: 3.10
Classifier: Topic :: Database
Classifier: Topic :: Software Development :: Libraries
Requires-Python: >=3.10
Requires-Dist: click
Requires-Dist: networkx>=3.3
Requires-Dist: packaging>=24.0
Requires-Dist: pydantic>=2.8.2
Requires-Dist: pyyaml>=6.0.1
Requires-Dist: rich
Requires-Dist: shellingham
Requires-Dist: sqlglot>=23.0.0
Requires-Dist: typer
Provides-Extra: dev
Requires-Dist: pytest-cov>=4.1.0; extra == 'dev'
Requires-Dist: pytest>=7.4.0; extra == 'dev'
